MM23084UNO/__init__.py
MM23084UNO/biseccion.py
MM23084UNO/cramer.py
MM23084UNO/gauss.py
MM23084UNO/gauss_jordan.py
MM23084UNO/gauss_seidel.py
MM23084UNO/jacobi.py
MM23084UNO/lu.py
mm23084uno-1.0.2.dist-info/licenses/LICENSE
mm23084uno-1.0.2.dist-info/METADATA
mm23084uno-1.0.2.dist-info/WHEEL
mm23084uno-1.0.2.dist-info/top_level.txt
mm23084uno-1.0.2.dist-info/RECORD
